setup.py
src/sqlalchemy_fp/__init__.py
src/sqlalchemy_fp/make_table_class_from.py
src/sqlalchemy_fp/prepare_models.py
src/sqlalchemy_fp/setup_reflective_engine.py
src/sqlalchemy_fp/setup_with_session.py
src/sqlalchemy_fp/with_session_from.py
src/sqlalchemy_fp.egg-info/PKG-INFO
src/sqlalchemy_fp.egg-info/SOURCES.txt
src/sqlalchemy_fp.egg-info/dependency_links.txt
src/sqlalchemy_fp.egg-info/not-zip-safe
src/sqlalchemy_fp.egg-info/requires.txt
src/sqlalchemy_fp.egg-info/top_level.txt