Metadata-Version: 1.0
Name: sqlalchemy-fp
Version: 0.1
Summary: A wrapper around SQLAlchemy for more functional ORM programming
Home-page: http://github.com/jackfirth/sqlalchemy-fp
Author: Jack Firth
Author-email: jackhfirth@gmail.com
License: UNKNOWN
Platform: UNKNOWN
